abhishek_topsis/__init__.py
abhishek_topsis-0.0.1.dist-info/LICENSE
abhishek_topsis-0.0.1.dist-info/METADATA
abhishek_topsis-0.0.1.dist-info/WHEEL
abhishek_topsis-0.0.1.dist-info/top_level.txt
abhishek_topsis-0.0.1.dist-info/RECORD
