Metadata-Version: 2.2
Name: abhishek_topsis
Version: 0.0.1
Summary: This Package will help you to calculate TOPSIS Score for multiple criteria...
Home-page: https://github.com/ABHISHEK-max-sketch/abhishek_topsis
Author: Abhishek Verma
Author-email: averma1_be22@thapar.edu
Project-URL: Bug Tracker, https://github.com/ABHISHEK-max-sketch/abhishek_topsis/issues
Classifier: Programming Language :: Python :: 3
Classifier: License :: OSI Approved :: MIT License
Classifier: Operating System :: OS Independent
Requires-Python: >=3.6
License-File: LICENSE
